{
  "id" : "orders_demo",
  "metainfo" : {
    "label" : "orders_demo",
    "autoLayout" : false,
    "staleState" : "none",
    "sourceSuggestions" : {
      "sources" : [ ]
    },
    "graphConfig" : {
      "userDefinedConfig" : {
        "vars" : { }
      }
    },
    "version" : 3
  },
  "processes" : {
    "source##LfZk4Lk2" : {
      "id" : "source##LfZk4Lk2",
      "component" : "Seed",
      "metadata" : {
        "label" : "source",
        "x" : -120,
        "y" : 20,
        "phase" : 0
      },
      "properties" : {
        "table" : {
          "name" : "raw_customers",
          "sourceType" : "Seed"
        }
      },
      "ports" : {
        "inputs" : [ ],
        "outputs" : [ {
          "id" : "haZeSK5G",
          "schema" : {
            "providerType" : "Databricks",
            "fields" : [ {
              "name" : "id",
              "dataType" : {
                "type" : "Integer"
              }
            }, {
              "name" : "first_name",
              "dataType" : {
                "type" : "String"
              }
            }, {
              "name" : "last_name",
              "dataType" : {
                "type" : "String"
              }
            } ]
          },
          "slug" : "out"
        } ],
        "isCustomOutputSchema" : false,
        "autoUpdateOnRun" : false
      }
    },
    "renamed##RPiXFzL3" : {
      "id" : "renamed##RPiXFzL3",
      "component" : "Reformat",
      "metadata" : {
        "label" : "renamed",
        "x" : 60,
        "y" : 20,
        "phase" : 0,
        "macroDependencies" : [ ]
      },
      "properties" : {
        "columnsSelector" : [ "-LjUVqTyh4JyVJWT0SomD##id", "-LjUVqTyh4JyVJWT0SomD##first_name", "-LjUVqTyh4JyVJWT0SomD##last_name" ],
        "expressions" : [ {
          "expression" : {
            "expression" : "id"
          }
        }, {
          "expression" : {
            "expression" : "first_name"
          }
        }, {
          "expression" : {
            "expression" : "last_name"
          }
        } ]
      },
      "ports" : {
        "inputs" : [ {
          "id" : "-LjUVqTyh4JyVJWT0SomD",
          "schema" : {
            "providerType" : "Databricks",
            "fields" : [ {
              "name" : "id",
              "dataType" : {
                "type" : "Integer"
              }
            }, {
              "name" : "first_name",
              "dataType" : {
                "type" : "String"
              }
            }, {
              "name" : "last_name",
              "dataType" : {
                "type" : "String"
              }
            } ]
          },
          "slug" : "source"
        } ],
        "outputs" : [ {
          "id" : "Cfi8rdtT",
          "schema" : {
            "providerType" : "Databricks",
            "fields" : [ {
              "name" : "id",
              "dataType" : {
                "type" : "Integer"
              }
            }, {
              "name" : "first_name",
              "dataType" : {
                "type" : "String"
              }
            }, {
              "name" : "last_name",
              "dataType" : {
                "type" : "String"
              }
            } ]
          },
          "slug" : "out"
        } ],
        "isCustomOutputSchema" : false,
        "autoUpdateOnRun" : false
      }
    },
    "orders_demo##tgEJp5if" : {
      "id" : "orders_demo##tgEJp5if",
      "component" : "TargetModel",
      "metadata" : {
        "label" : "orders_demo",
        "x" : 220,
        "y" : 20,
        "phase" : 0,
        "macroDependencies" : [ ]
      },
      "properties" : {
        "customQueryDisabled" : true,
        "customQuery" : false,
        "incrementalEditorDisabled" : true,
        "query" : "SELECT * \n\nFROM renamed\n",
        "isModel" : false,
        "incrementalKey" : false,
        "incremental" : {
          "expression" : "true"
        }
      },
      "ports" : {
        "inputs" : [ {
          "id" : "uXT8wBWB",
          "schema" : {
            "providerType" : "Databricks",
            "fields" : [ {
              "name" : "id",
              "dataType" : {
                "type" : "Integer"
              }
            }, {
              "name" : "first_name",
              "dataType" : {
                "type" : "String"
              }
            }, {
              "name" : "last_name",
              "dataType" : {
                "type" : "String"
              }
            } ]
          },
          "slug" : "renamed"
        } ],
        "outputs" : [ {
          "id" : "eCASAxMS",
          "schema" : {
            "providerType" : "Databricks",
            "fields" : [ {
              "name" : "id",
              "dataType" : {
                "type" : "Integer"
              }
            }, {
              "name" : "first_name",
              "dataType" : {
                "type" : "String"
              }
            }, {
              "name" : "last_name",
              "dataType" : {
                "type" : "String"
              }
            } ]
          },
          "slug" : "out"
        } ],
        "isCustomOutputSchema" : false,
        "autoUpdateOnRun" : false
      }
    }
  },
  "connections" : [ {
    "id" : "ZF9us8cD",
    "source" : "renamed##RPiXFzL3",
    "sourcePort" : "Cfi8rdtT",
    "target" : "orders_demo##tgEJp5if",
    "targetPort" : "uXT8wBWB"
  }, {
    "id" : "z9U82sspXfNAd-NG8SGPA",
    "source" : "source##LfZk4Lk2",
    "sourcePort" : "haZeSK5G",
    "target" : "renamed##RPiXFzL3",
    "targetPort" : "-LjUVqTyh4JyVJWT0SomD"
  } ],
  "component" : "Model"
}